opencroplib/__init__.py
opencroplib/aerodynamic.py
opencroplib/atmophere.py
opencroplib/evapotranspiration.py
opencroplib/plant.py
opencroplib/radiation.py
opencroplib/test_opencroplib.py
opencroplib/time_utils.py
opencroplib-0.1.6.dist-info/LICENSE.txt
opencroplib-0.1.6.dist-info/METADATA
opencroplib-0.1.6.dist-info/WHEEL
opencroplib-0.1.6.dist-info/top_level.txt
opencroplib-0.1.6.dist-info/RECORD
