Metadata-Version: 2.1
Name: opencroplib
Version: 0.1.6
Summary: Python Library for simulating physiological processes in plants
Home-page: https://github.com/OpenAgriTech/opencroplib
Author: Jose A. Jimenez-Berni
Author-email: berni@ias.csic.es
License: LICENSE.txt
Platform: UNKNOWN
Classifier: Development Status :: 3 - Alpha
Classifier: Programming Language :: Python :: 2.7
Classifier: Programming Language :: Python :: 3
Classifier: License :: OSI Approved :: MIT License
Classifier: Operating System :: OS Independent
Classifier: Intended Audience :: Science/Research
Classifier: Topic :: Scientific/Engineering
Classifier: Topic :: Scientific/Engineering :: Atmospheric Science
License-File: LICENSE.txt
Requires-Dist: python (>=2.7)
Requires-Dist: numpy
Requires-Dist: pytz
Requires-Dist: pandas
